README.rst
setup.py
src/nodeconductor_auth_openid/__init__.py
src/nodeconductor_auth_openid/apps.py
src/nodeconductor_auth_openid/auth.py
src/nodeconductor_auth_openid/extension.py
src/nodeconductor_auth_openid/log.py
src/nodeconductor_auth_openid/urls.py
src/nodeconductor_auth_openid/views.py
src/nodeconductor_auth_openid.egg-info/PKG-INFO
src/nodeconductor_auth_openid.egg-info/SOURCES.txt
src/nodeconductor_auth_openid.egg-info/dependency_links.txt
src/nodeconductor_auth_openid.egg-info/entry_points.txt
src/nodeconductor_auth_openid.egg-info/not-zip-safe
src/nodeconductor_auth_openid.egg-info/requires.txt
src/nodeconductor_auth_openid.egg-info/top_level.txt
src/nodeconductor_auth_openid/migrations/0001_update_nicknames.py
src/nodeconductor_auth_openid/migrations/0002_username_uuid.py
src/nodeconductor_auth_openid/migrations/__init__.py