Metadata-Version: 1.1
Name: nodeconductor-auth-openid
Version: 0.8.4
Summary: Waldur plugin bringing OpenID-based authentication support.
Home-page: http://waldur.com
Author: OpenNode Team
Author-email: info@opennodecloud.com
License: MIT
Platform: UNKNOWN
Classifier: Framework :: Django
Classifier: Intended Audience :: Developers
Classifier: Intended Audience :: System Administrators
Classifier: Operating System :: OS Independent
Classifier: License :: OSI Approved :: MIT License
